progress_list.py
progress_list-0.1.0.dist-info/licenses/LICENSE
progress_list-0.1.0.dist-info/METADATA
progress_list-0.1.0.dist-info/WHEEL
progress_list-0.1.0.dist-info/entry_points.txt
progress_list-0.1.0.dist-info/top_level.txt
progress_list-0.1.0.dist-info/RECORD
